gerritqueue/__init__.py
gerritqueue/gerrit.py
gerritqueue/main.py
gerritqueue/rqueue.py
gerritqueue/version.py
gerritqueue-1.0.2.dist-info/LICENSE
gerritqueue-1.0.2.dist-info/METADATA
gerritqueue-1.0.2.dist-info/WHEEL
gerritqueue-1.0.2.dist-info/entry_points.txt
gerritqueue-1.0.2.dist-info/top_level.txt
gerritqueue-1.0.2.dist-info/RECORD
