Metadata-Version: 2.1
Name: gerritqueue
Version: 1.0.2
Summary: Gerrit event queue
Home-page: https://github.com/craftslab/gerritqueue
Author: Jia Jia
Author-email: angersax@sina.com
License: Apache-2.0
Download-URL: https://github.com/craftslab/gerritqueue/archive/v1.0.2.tar.gz
Keywords: gerrit,event,queue
Platform: UNKNOWN
Classifier: Programming Language :: Python :: 3
Classifier: License :: OSI Approved :: Apache Software License
Classifier: Operating System :: OS Independent
Requires-Dist: redis
Requires-Dist: requests
